CHANGES.txt
CONTRIBUTORS.txt
MANIFEST.in
README.rst
setup.py
src/rebecca/__init__.py
src/rebecca.testing.egg-info/PKG-INFO
src/rebecca.testing.egg-info/SOURCES.txt
src/rebecca.testing.egg-info/dependency_links.txt
src/rebecca.testing.egg-info/entry_points.txt
src/rebecca.testing.egg-info/namespace_packages.txt
src/rebecca.testing.egg-info/not-zip-safe
src/rebecca.testing.egg-info/requires.txt
src/rebecca.testing.egg-info/top_level.txt
src/rebecca/testing/__init__.py