Metadata-Version: 1.1
Name: rebecca.testing
Version: 0.1
Summary: UNKNOWN
Home-page: https://github.com/rebeccaframework/rebecca.testing
Author: Atsushi Odagiri
Author-email: aodagx@gmail.com
License: MIT
Platform: UNKNOWN
Classifier: Programming Language :: Python
Classifier: Programming Language :: Python :: 2.7
Classifier: Programming Language :: Python :: 3
Classifier: Programming Language :: Python :: 3.3
